[
  {
    "text": "原谅我这一生不羁放纵爱自由",
    "source": "海阔天空",
    "author": "Beyond",
    "category": "歌词"
  },
  {
    "text": "今天我寒夜里看雪飘过，怀着冷却了的心窝漂远方",
    "source": "光辉岁月",
    "author": "Beyond",
    "category": "歌词"
  },
  {
    "text": "天空海阔你与我，可会改变",
    "source": "海阔天空",
    "author": "Beyond",
    "category": "歌词"
  },
  {
    "text": "被偏爱的都有恃无恐",
    "source": "红玫瑰",
    "author": "陈奕迅",
    "category": "歌词"
  },
  {
    "text": "得不到的永远在骚动",
    "source": "红玫瑰",
    "author": "陈奕迅",
    "category": "歌词"
  },
  {
    "text": "为你我用了半年的积蓄，漂洋过海地来看你",
    "source": "漂洋过海来看你",
    "author": "娃娃",
    "category": "歌词"
  },
  {
    "text": "十年之前，我不认识你，你不属于我",
    "source": "十年",
    "author": "陈奕迅",
    "category": "歌词"
  },
  {
    "text": "明明是三个人的电影，我却始终不能有姓名",
    "source": "暗里着迷",
    "author": "陈奕迅",
    "category": "歌词"
  },
  {
    "text": "陪你度过漫长岁月",
    "source": "陪你度过漫长岁月",
    "author": "陈奕迅",
    "category": "歌词"
  },
  {
    "text": "如果时光只能回到那一刻，我会选择什么都不说",
    "source": "富士山下",
    "author": "林夕",
    "category": "歌词"
  },
  {
    "text": "谁能凭爱意要富士山私有",
    "source": "富士山下",
    "author": "陈奕迅",
    "category": "歌词"
  },
  {
    "text": "爱情不是你想买，想买就能买",
    "source": "两只蝴蝶",
    "author": "庞龙",
    "category": "歌词"
  },
  {
    "text": "想说却还没说的，还很多",
    "source": "晴天",
    "author": "周杰伦",
    "category": "歌词"
  },
  {
    "text": "故事的小黄花，从出生那年就飘着",
    "source": "晴天",
    "author": "周杰伦",
    "category": "歌词"
  },
  {
    "text": "天青色等烟雨，而我在等你",
    "source": "青花瓷",
    "author": "方文山",
    "category": "歌词"
  },
  {
    "text": "窗外的麻雀，在电线杆上多嘴",
    "source": "七里香",
    "author": "周杰伦",
    "category": "歌词"
  },
  {
    "text": "听妈妈的话，别让她受伤",
    "source": "听妈妈的话",
    "author": "周杰伦",
    "category": "歌词"
  },
  {
    "text": "我送你离开千里之外，你无声黑白",
    "source": "千里之外",
    "author": "周杰伦",
    "category": "歌词"
  },
  {
    "text": "想要有直升机，想要和你飞到宇宙去",
    "source": "简单爱",
    "author": "周杰伦",
    "category": "歌词"
  },
  {
    "text": "我不是你的谁，你也不是我的谁",
    "source": "温柔",
    "author": "五月天",
    "category": "歌词"
  },
  {
    "text": "如果我有梦，有一个像海一样的梦",
    "source": "如烟",
    "author": "五月天",
    "category": "歌词"
  },
  {
    "text": "知道你的好，知道你会来，所以我等待",
    "source": "突然好想你",
    "author": "五月天",
    "category": "歌词"
  },
  {
    "text": "当我和世界不一样，那就让我不一样",
    "source": "倔强",
    "author": "五月天",
    "category": "歌词"
  },
  {
    "text": "我曾经跨过山和大海，也穿过人山人海",
    "source": "平凡之路",
    "author": "朴树",
    "category": "歌词"
  },
  {
    "text": "那些花儿，开在我生命的每一个角落",
    "source": "那些花儿",
    "author": "朴树",
    "category": "歌词"
  },
  {
    "text": "时间被磨成了铁，会卷起怎样的浪",
    "source": "清白之年",
    "author": "朴树",
    "category": "歌词"
  },
  {
    "text": "我们就这样各自奔天涯",
    "source": "那些花儿",
    "author": "朴树",
    "category": "歌词"
  },
  {
    "text": "想要问问你敢不敢，像你说过那样地爱我",
    "source": "恋曲1990",
    "author": "罗大佑",
    "category": "歌词"
  },
  {
    "text": "轰隆隆的雷雨声，在浮云堆里响着",
    "source": "光阴的故事",
    "author": "罗大佑",
    "category": "歌词"
  },
  {
    "text": "越过山丘，才发现无人等候",
    "source": "山丘",
    "author": "李宗盛",
    "category": "歌词"
  },
  {
    "text": "想得却不可得，你奈人生何",
    "source": "山丘",
    "author": "李宗盛",
    "category": "歌词"
  },
  {
    "text": "她的眼神，没有改变，是我们改变了世界",
    "source": "凡人歌",
    "author": "李宗盛",
    "category": "歌词"
  },
  {
    "text": "但愿人长久，千里共婵娟",
    "source": "但愿人长久",
    "author": "王菲",
    "category": "歌词"
  },
  {
    "text": "原来你非不快乐，只我未发现",
    "source": "再见二丁目",
    "author": "林夕",
    "category": "歌词"
  },
  {
    "text": "长风破浪会有时，直挂云帆济沧海。",
    "source": "行路难",
    "author": "李白",
    "category": "诗词"
  },
  {
    "text": "天生我材必有用，千金散尽还复来。",
    "source": "将进酒",
    "author": "李白",
    "category": "诗词"
  },
  {
    "text": "举头望明月，低头思故乡。",
    "source": "静夜思",
    "author": "李白",
    "category": "诗词"
  },
  {
    "text": "安能摧眉折腰事权贵，使我不得开心颜。",
    "source": "梦游天姥吟留别",
    "author": "李白",
    "category": "诗词"
  },
  {
    "text": "会当凌绝顶，一览众山小。",
    "source": "望岳",
    "author": "杜甫",
    "category": "诗词"
  },
  {
    "text": "随风潜入夜，润物细无声。",
    "source": "春夜喜雨",
    "author": "杜甫",
    "category": "诗词"
  },
  {
    "text": "安得广厦千万间，大庇天下寒士俱欢颜。",
    "source": "茅屋为秋风所破歌",
    "author": "杜甫",
    "category": "诗词"
  },
  {
    "text": "但愿人长久，千里共婵娟。",
    "source": "水调歌头",
    "author": "苏轼",
    "category": "诗词"
  },
  {
    "text": "人生如梦，一尊还酹江月。",
    "source": "念奴娇·赤壁怀古",
    "author": "苏轼",
    "category": "诗词"
  },
  {
    "text": "竹杖芒鞋轻胜马，谁怕？一蓑烟雨任平生。",
    "source": "定风波",
    "author": "苏轼",
    "category": "诗词"
  },
  {
    "text": "十年生死两茫茫，不思量，自难忘。",
    "source": "江城子·乙卯正月二十日夜记梦",
    "author": "苏轼",
    "category": "诗词"
  },
  {
    "text": "莫等闲，白了少年头，空悲切。",
    "source": "满江红",
    "author": "岳飞",
    "category": "诗词"
  },
  {
    "text": "寻寻觅觅，冷冷清清，凄凄惨惨戚戚。",
    "source": "声声慢",
    "author": "李清照",
    "category": "诗词"
  },
  {
    "text": "生当作人杰，死亦为鬼雄。",
    "source": "夏日绝句",
    "author": "李清照",
    "category": "诗词"
  },
  {
    "text": "莫道不消魂，帘卷西风，人比黄花瘦。",
    "source": "醉花阴",
    "author": "李清照",
    "category": "诗词"
  },
  {
    "text": "行到水穷处，坐看云起时。",
    "source": "终南别业",
    "author": "王维",
    "category": "诗词"
  },
  {
    "text": "独在异乡为异客，每逢佳节倍思亲。",
    "source": "九月九日忆山东兄弟",
    "author": "王维",
    "category": "诗词"
  },
  {
    "text": "大漠孤烟直，长河落日圆。",
    "source": "使至塞上",
    "author": "王维",
    "category": "诗词"
  },
  {
    "text": "身无彩凤双飞翼，心有灵犀一点通。",
    "source": "无题",
    "author": "李商隐",
    "category": "诗词"
  },
  {
    "text": "春蚕到死丝方尽，蜡炬成灰泪始干。",
    "source": "无题",
    "author": "李商隐",
    "category": "诗词"
  },
  {
    "text": "夕阳无限好，只是近黄昏。",
    "source": "乐游原",
    "author": "李商隐",
    "category": "诗词"
  },
  {
    "text": "此情可待成追忆，只是当时已惘然。",
    "source": "锦瑟",
    "author": "李商隐",
    "category": "诗词"
  },
  {
    "text": "人生若只如初见，何事秋风悲画扇。",
    "source": "木兰花·拟古决绝词柬友",
    "author": "纳兰性德",
    "category": "诗词"
  },
  {
    "text": "赌书消得泼茶香，当时只道是寻常。",
    "source": "浣溪沙",
    "author": "纳兰性德",
    "category": "诗词"
  },
  {
    "text": "众里寻他千百度，蓦然回首，那人却在，灯火阑珊处。",
    "source": "青玉案·元夕",
    "author": "辛弃疾",
    "category": "诗词"
  },
  {
    "text": "了却君王天下事，赢得生前身后名。可怜白发生。",
    "source": "破阵子·为陈同甫赋壮词以寄之",
    "author": "辛弃疾",
    "category": "诗词"
  },
  {
    "text": "少年不识愁滋味，爱上层楼。",
    "source": "丑奴儿·书博山道中壁",
    "author": "辛弃疾",
    "category": "诗词"
  },
  {
    "text": "枯藤老树昏鸦，小桥流水人家，古道西风瘦马。",
    "source": "天净沙·秋思",
    "author": "马致远",
    "category": "诗词"
  },
  {
    "text": "问君能有几多愁？恰似一江春水向东流。",
    "source": "虞美人",
    "author": "李煜",
    "category": "诗词"
  },
  {
    "text": "落霞与孤鹜齐飞，秋水共长天一色。",
    "source": "滕王阁序",
    "author": "王勃",
    "category": "诗词"
  },
  {
    "text": "海内存知己，天涯若比邻。",
    "source": "送杜少府之任蜀州",
    "author": "王勃",
    "category": "诗词"
  },
  {
    "text": "沉舟侧畔千帆过，病树前头万木春。",
    "source": "酬乐天扬州初逢席上见赠",
    "author": "刘禹锡",
    "category": "诗词"
  },
  {
    "text": "曾经有一份真诚的爱情摆在我面前，我没有珍惜，等我失去的时候才后悔莫及。",
    "source": "大话西游",
    "author": "至尊宝",
    "category": "电影"
  },
  {
    "text": "如果非要在这份爱上加上一个期限，我希望是一万年。",
    "source": "大话西游",
    "author": "至尊宝",
    "category": "电影"
  },
  {
    "text": "你看那个人，好奇怪喔，像一条狗。",
    "source": "大话西游",
    "author": "紫霞仙子",
    "category": "电影"
  },
  {
    "text": "说好了是一辈子，差一年、一个月、一天、一个时辰，都不算一辈子。",
    "source": "霸王别姬",
    "author": "程蝶衣",
    "category": "电影"
  },
  {
    "text": "不疯魔，不成活。",
    "source": "霸王别姬",
    "category": "电影"
  },
  {
    "text": "生活就像一盒巧克力，你永远不知道下一颗是什么味道。",
    "source": "阿甘正传",
    "author": "阿甘",
    "category": "电影"
  },
  {
    "text": "妈妈说，死亡是生命的一部分。",
    "source": "阿甘正传",
    "author": "阿甘",
    "category": "电影"
  },
  {
    "text": "生命会自己找到出路。",
    "source": "侏罗纪公园",
    "category": "电影"
  },
  {
    "text": "你是不是又把枪带回家了？",
    "source": "这个杀手不太冷",
    "category": "电影"
  },
  {
    "text": "生活是不是永远这么艰难，还是只有童年如此？——总是如此。",
    "source": "这个杀手不太冷",
    "category": "电影"
  },
  {
    "text": "我宁可一辈子待在船上，从这头走到那头，也不愿在无边无际的城市里迷失。",
    "source": "海上钢琴师",
    "author": "1900",
    "category": "电影"
  },
  {
    "text": "陆地上的人喜欢寻根问底，虚度了大好光阴。",
    "source": "海上钢琴师",
    "author": "1900",
    "category": "电影"
  },
  {
    "text": "你跳，我也跳。",
    "source": "泰坦尼克号",
    "author": "杰克",
    "category": "电影"
  },
  {
    "text": "做人没有梦想，跟咸鱼有什么分别？",
    "source": "少林足球",
    "category": "电影"
  },
  {
    "text": "难一步，佳一步。",
    "source": "岁月神偷",
    "category": "电影"
  },
  {
    "text": "鞋子合不合适，只有脚知道。",
    "source": "花样年华",
    "category": "电影"
  },
  {
    "text": "如果多一张船票，你会不会跟我一起走？",
    "source": "花样年华",
    "category": "电影"
  },
  {
    "text": "有些鸟儿是关不住的，它们的每一片羽毛都闪耀着自由的光辉。",
    "source": "肖申克的救赎",
    "category": "电影"
  },
  {
    "text": "懦怯囚禁人的灵魂，希望可以感受自由。",
    "source": "肖申克的救赎",
    "category": "电影"
  },
  {
    "text": "希望是美好的，也许是人间至善，而美好的事物永不消逝。",
    "source": "肖申克的救赎",
    "author": "安迪",
    "category": "电影"
  },
  {
    "text": "我会回来的。",
    "source": "终结者",
    "category": "电影"
  },
  {
    "text": "愿原力与你同在。",
    "source": "星球大战",
    "category": "电影"
  },
  {
    "text": "逝者已矣，生者如斯。",
    "source": "狮子王",
    "category": "电影"
  },
  {
    "text": "过去是痛苦的，但你可以选择逃避，或者从中学到东西。",
    "source": "狮子王",
    "category": "电影"
  },
  {
    "text": "人生不相见，动如参与商。",
    "source": "无间道",
    "category": "电影"
  },
  {
    "text": "出来混，迟早要还的。",
    "source": "无间道",
    "category": "电影"
  },
  {
    "text": "我猜中了前头，可是我猜不着这结局。",
    "source": "大话西游",
    "category": "电影"
  },
  {
    "text": "念念不忘，必有回响。",
    "source": "一代宗师",
    "category": "电影"
  },
  {
    "text": "世间所有的相遇，都是久别重逢。",
    "source": "一代宗师",
    "category": "电影"
  },
  {
    "text": "我们一直活在记忆中，时而想起昨日种种。",
    "source": "哈尔的移动城堡",
    "author": "哈尔",
    "category": "电影"
  },
  {
    "text": "曾经爱过你，是我做过最好的事。",
    "source": "恋恋笔记本",
    "category": "电影"
  },
  {
    "text": "希望是本无所谓有，无所谓无的。这正如地上的路；其实地上本没有路，走的人多了，也便成了路。",
    "source": "故乡",
    "author": "鲁迅",
    "category": "文学"
  },
  {
    "text": "猛兽总是独行，牛羊才成群结队。",
    "author": "鲁迅",
    "category": "文学"
  },
  {
    "text": "于浩歌狂热之际中寒；于天上看见深渊。",
    "source": "墓碣文",
    "author": "鲁迅",
    "category": "文学"
  },
  {
    "text": "愿中国青年都摆脱冷气，只是向上走，不必听自暴自弃者流的话。",
    "source": "热风",
    "author": "鲁迅",
    "category": "文学"
  },
  {
    "text": "也许爱不是热情，也不是怀念，不过是岁月，年深月久成了生活的一部分。",
    "source": "半生缘",
    "author": "张爱玲",
    "category": "文学"
  },
  {
    "text": "于千万人之中遇见你所要遇见的人，没有早一步，也没有晚一步，刚巧赶上了。",
    "source": "爱",
    "author": "张爱玲",
    "category": "文学"
  },
  {
    "text": "生命是一袭华美的袍，爬满了蚤子。",
    "source": "天才梦",
    "author": "张爱玲",
    "category": "文学"
  },
  {
    "text": "岁月静好，现世安稳。",
    "author": "张爱玲",
    "category": "文学"
  },
  {
    "text": "从前的日色变得慢，车，马，邮件都慢，一生只够爱一个人。",
    "source": "从前慢",
    "author": "木心",
    "category": "文学"
  },
  {
    "text": "岁月不饶人，我亦未曾饶过岁月。",
    "author": "木心",
    "category": "文学"
  },
  {
    "text": "所谓无底深渊，下去，也是前程万里。",
    "author": "木心",
    "category": "文学"
  },
  {
    "text": "我明白你会来，所以我等。",
    "source": "雨后",
    "author": "沈从文",
    "category": "文学"
  },
  {
    "text": "这个人也许永远不回来了，也许明天回来。",
    "source": "边城",
    "author": "沈从文",
    "category": "文学"
  },
  {
    "text": "我行过许多地方的桥，看过许多次数的云，喝过许多种类的酒，却只爱过一个正当最好年龄的人。",
    "author": "沈从文",
    "category": "文学"
  },
  {
    "text": "围在城里的人想逃出来，城外的人想冲进去。婚姻也罢，职业也罢，人生的愿望大都如此。",
    "source": "围城",
    "author": "钱钟书",
    "category": "文学"
  },
  {
    "text": "忠厚老实人的恶毒，像饭里的沙砾或者出骨鱼片里的刺，会给人一种不期待的伤痛。",
    "source": "围城",
    "author": "钱钟书",
    "category": "文学"
  },
  {
    "text": "人生忽如寄，莫负茶汤好天气。",
    "author": "汪曾祺",
    "category": "文学"
  },
  {
    "text": "如果你来访我，我不在，请和我门外的花坐一会儿。",
    "author": "汪曾祺",
    "category": "文学"
  },
  {
    "text": "一定要爱着点什么，恰似草木对光阴的钟情。",
    "author": "汪曾祺",
    "category": "文学"
  },
  {
    "text": "生活，是很好玩的。",
    "author": "汪曾祺",
    "category": "文学"
  },
  {
    "text": "许多年之后，面对行刑队，奥雷里亚诺·布恩迪亚上校将会回想起父亲带他去见识冰块的那个遥远的下午。",
    "source": "百年孤独",
    "author": "加西亚·马尔克斯",
    "category": "文学"
  },
  {
    "text": "过去都是假的，回忆是一条没有归途的路。",
    "source": "百年孤独",
    "author": "加西亚·马尔克斯",
    "category": "文学"
  },
  {
    "text": "死亡不是失去生命，而是走出了时间。",
    "source": "百年孤独",
    "author": "加西亚·马尔克斯",
    "category": "文学"
  },
  {
    "text": "每个人都不是一座孤岛，而我们终将彼此相连。",
    "author": "村上春树",
    "category": "文学"
  },
  {
    "text": "哪里会有人喜欢孤独，不过是不喜欢失望罢了。",
    "source": "挪威的森林",
    "author": "村上春树",
    "category": "文学"
  },
  {
    "text": "不必太纠结于当下，也不必太忧虑未来，当你经历过一些事情的时候，眼前的风景已经和从前不一样了。",
    "author": "村上春树",
    "category": "文学"
  },
  {
    "text": "在隆冬，我终于知道，我身上有一个不可战胜的夏天。",
    "source": "夏天集",
    "author": "加缪",
    "category": "文学"
  },
  {
    "text": "对未来真正的慷慨，是把一切献给现在。",
    "source": "反抗者",
    "author": "加缪",
    "category": "文学"
  },
  {
    "text": "我们必须想象西西弗是幸福的。",
    "source": "西西弗神话",
    "author": "加缪",
    "category": "文学"
  },
  {
    "text": "卑鄙是卑鄙者的通行证，高尚是高尚者的墓志铭。",
    "source": "回答",
    "author": "北岛",
    "category": "文学"
  },
  {
    "text": "使我们感动的不是岁月的力量，而是人对岁月的态度。",
    "source": "月亮与六便士",
    "author": "毛姆",
    "category": "文学"
  },
  {
    "text": "她那时候还太年轻，不知道所有命运赠送的礼物，早已在暗中标好了价格。",
    "source": "断头王后",
    "author": "茨威格",
    "category": "文学"
  },
  {
    "text": "那些杀不死我的，使我更强大。",
    "author": "尼采",
    "category": "哲思"
  },
  {
    "text": "当你凝视深渊时，深渊也在凝视着你。",
    "author": "尼采",
    "category": "哲思"
  },
  {
    "text": "每一个不曾起舞的日子，都是对生命的辜负。",
    "author": "尼采",
    "category": "哲思"
  },
  {
    "text": "真正严肃的哲学问题只有一个，那就是自杀。",
    "source": "西西弗神话",
    "author": "加缪",
    "category": "哲思"
  },
  {
    "text": "认识你自己。",
    "author": "苏格拉底",
    "category": "哲思"
  },
  {
    "text": "未经省察的人生不值得过。",
    "author": "苏格拉底",
    "category": "哲思"
  },
  {
    "text": "我唯一知道的，就是我一无所知。",
    "author": "苏格拉底",
    "category": "哲思"
  },
  {
    "text": "人不能两次踏进同一条河流。",
    "author": "赫拉克利特",
    "category": "哲思"
  },
  {
    "text": "生命是一团欲望，欲望不满足便痛苦，满足便无聊。",
    "author": "叔本华",
    "category": "哲思"
  },
  {
    "text": "要么孤独，要么庸俗。",
    "author": "叔本华",
    "category": "哲思"
  },
  {
    "text": "我们要么生活在痛苦中，要么生活在无聊中。",
    "author": "叔本华",
    "category": "哲思"
  },
  {
    "text": "我们都生活在阴沟里，但仍有人仰望星空。",
    "author": "王尔德",
    "category": "哲思"
  },
  {
    "text": "做你自己，因为别人都有人做了。",
    "author": "王尔德",
    "category": "哲思"
  },
  {
    "text": "对幸福的恐惧，往往是不幸的根源。",
    "author": "罗素",
    "category": "哲思"
  },
  {
    "text": "参差多态，乃是幸福的本源。",
    "author": "罗素",
    "category": "哲思"
  },
  {
    "text": "对爱情的渴望，对知识的追求，对人类苦难不可遏制的同情，支配着我的一生。",
    "author": "罗素",
    "category": "哲思"
  },
  {
    "text": "吾生也有涯，而知也无涯。",
    "source": "庄子",
    "author": "庄子",
    "category": "哲思"
  },
  {
    "text": "井蛙不可以语于海者，拘于虚也。",
    "source": "庄子",
    "author": "庄子",
    "category": "哲思"
  },
  {
    "text": "相濡以沫，不如相忘于江湖。",
    "source": "庄子",
    "author": "庄子",
    "category": "哲思"
  },
  {
    "text": "上善若水，水善利万物而不争。",
    "source": "道德经",
    "author": "老子",
    "category": "哲思"
  },
  {
    "text": "知人者智，自知者明。",
    "source": "道德经",
    "author": "老子",
    "category": "哲思"
  },
  {
    "text": "祸兮福之所倚，福兮祸之所伏。",
    "source": "道德经",
    "author": "老子",
    "category": "哲思"
  },
  {
    "text": "人生本无意义，是我们使它有意义。",
    "author": "周国平",
    "category": "哲思"
  },
  {
    "text": "经历就是体验，体验得越深，生命的意义就越丰富。",
    "author": "周国平",
    "category": "哲思"
  },
  {
    "text": "未经审视的爱不值得拥有，未经爱的审视不值得信赖。",
    "author": "周国平",
    "category": "哲思"
  },
  {
    "text": "人是要有一点精神的。",
    "author": "周国平",
    "category": "哲思"
  },
  {
    "text": "我思故我在。",
    "author": "笛卡尔",
    "category": "哲思"
  },
  {
    "text": "人是一根会思想的苇草。",
    "source": "思想录",
    "author": "帕斯卡",
    "category": "哲思"
  },
  {
    "text": "人生而自由，却无往不在枷锁之中。",
    "source": "社会契约论",
    "author": "卢梭",
    "category": "哲思"
  },
  {
    "text": "我们所能犯的最大错误，是一辈子担心犯错。",
    "author": "哈伯德",
    "category": "哲思"
  },
  {
    "text": "愿你慢慢长大，愿你有好运气，如果没有，愿你在不幸中学会慈悲。",
    "source": "愿你慢慢长大",
    "author": "刘瑜",
    "category": "语录"
  },
  {
    "text": "人的一切痛苦，本质上都是对自己无能的愤怒。",
    "author": "王小波",
    "category": "语录"
  },
  {
    "text": "一个人只拥有此生此世是不够的，他还应该拥有诗意的世界。",
    "author": "王小波",
    "category": "语录"
  },
  {
    "text": "我们曾如此渴望命运的波澜，到最后才发现，人生最曼妙的风景，竟是内心的淡定与从容。",
    "author": "杨绛",
    "category": "语录"
  },
  {
    "text": "世界上只有一种真正的英雄主义，那就是认清生活的真相后依然热爱生活。",
    "author": "罗曼·罗兰",
    "category": "语录"
  },
  {
    "text": "你要做一个不动声色的大人了，不准情绪化，不准偷偷想念，不准回头看。",
    "author": "村上春树",
    "category": "语录"
  },
  {
    "text": "哪有什么胜利可言，挺住意味着一切。",
    "author": "里尔克",
    "category": "语录"
  },
  {
    "text": "愿你被这个世界温柔以待。",
    "category": "语录"
  },
  {
    "text": "生活明朗，万物可爱，人间值得，未来可期。",
    "category": "语录"
  },
  {
    "text": "星星之所以发光，是为了让每一个人有一天都能找到属于自己的星星。",
    "source": "小王子",
    "author": "圣埃克苏佩里",
    "category": "语录"
  },
  {
    "text": "正是你为你的玫瑰花费的时光，才使你的玫瑰变得如此重要。",
    "source": "小王子",
    "author": "圣埃克苏佩里",
    "category": "语录"
  },
  {
    "text": "如果你想造一艘船，先唤起人们对大海的向往。",
    "author": "圣埃克苏佩里",
    "category": "语录"
  },
  {
    "text": "凡是过往，皆为序章。",
    "source": "暴风雨",
    "author": "莎士比亚",
    "category": "语录"
  },
  {
    "text": "黑夜无论怎样悠长，白昼总会到来。",
    "source": "麦克白",
    "author": "莎士比亚",
    "category": "语录"
  },
  {
    "text": "我们都在阴沟里，但仍有人仰望星空。",
    "author": "王尔德",
    "category": "语录"
  },
  {
    "text": "去爱具体的人，不要爱抽象的人；去做具体的事，不要做抽象的事。",
    "category": "语录"
  },
  {
    "text": "万物皆有裂痕，那是光照进来的地方。",
    "source": "Anthem",
    "author": "莱昂纳德·科恩",
    "category": "语录"
  },
  {
    "text": "今天迈出的一小步，是明天回望时的一大步。",
    "category": "语录"
  },
  {
    "text": "愿你出走半生，归来仍是少年。",
    "author": "苏轼",
    "category": "语录"
  },
  {
    "text": "人生如逆旅，我亦是行人。",
    "source": "临江仙·送钱穆父",
    "author": "苏轼",
    "category": "语录"
  },
  {
    "text": "一蓑烟雨任平生。",
    "source": "定风波",
    "author": "苏轼",
    "category": "语录"
  },
  {
    "text": "晚来天欲雪，能饮一杯无。",
    "source": "问刘十九",
    "author": "白居易",
    "category": "语录"
  },
  {
    "text": "我们最大的光荣不在于从不跌倒，而在于每次跌倒后都能爬起来。",
    "category": "语录"
  },
  {
    "text": "你今日的从容，是过往无数次咬牙坚持换来的。",
    "category": "语录"
  },
  {
    "text": "慢慢来，比较快。",
    "category": "语录"
  },
  {
    "text": "心若没有栖息的地方，到哪里都是流浪。",
    "author": "三毛",
    "category": "语录"
  },
  {
    "text": "岁月极美，在于它必然的流逝。春花、秋月、夏日、冬雪。",
    "author": "三毛",
    "category": "语录"
  },
  {
    "text": "愿有岁月可回首，且以深情共白头。",
    "category": "语录"
  },
  {
    "text": "所有的相遇都是久别重逢。",
    "author": "白落梅",
    "category": "语录"
  }
]